README.txt
setup.cfg
setup.py
utils/dutest.py
utils/dutest.egg-info/PKG-INFO
utils/dutest.egg-info/SOURCES.txt
utils/dutest.egg-info/dependency_links.txt
utils/dutest.egg-info/top_level.txt
