Metadata-Version: 1.1
Name: dutest
Version: 0.2.2
Summary: An object-oriented API to test doctests using unittest runners.
Home-page: http://flioops.sourceforge.net
Author: Olemis Lang
Author-email: olemis@gmail.com
License: UNKNOWN
Download-URL: https://sourceforge.net/project/showfiles.php?group_id=220287&package_id=265911
Platform: UNKNOWN
Classifier: Development Status :: 3 - Alpha
Classifier: Intended Audience :: Developers
Classifier: Intended Audience :: Information Technology
Classifier: License :: OSI Approved :: Python Software Foundation License
Classifier: Natural Language :: English
Classifier: Natural Language :: Spanish
Classifier: Operating System :: OS Independent
Classifier: Programming Language :: Python
Classifier: Topic :: Documentation
Classifier: Topic :: Education :: Testing
Classifier: Topic :: Software Development :: Documentation
Classifier: Topic :: Software Development :: Libraries :: Python Modules
Classifier: Topic :: Software Development :: Quality Assurance
Classifier: Topic :: Software Development :: Testing
Requires: doctest
Requires: unittest
Provides: dutest (0.2.2)
Obsoletes: dutest (<=0.2.1)
